{
  "Version": "2012-10-17",
  "Statement": [
    {
      "Effect": "Allow",
      "Action": [
        "iam:CreateServiceLinkedRole",
        "iam:GetServerCertificate",
        "iam:ListServerCertificates",
        "iam:ListRoles",
        "iam:AttachRolePolicy",
        "iam:PutRolePolicy",
        "iam:DeleteRolePolicy",
        "iam:DeleteServiceLinkedRole",
        "ec2:DescribeAccountAttributes",
        "ec2:DescribeAddresses",
        "ec2:DescribeInstances",
        "ec2:DescribeInternetGateways",
        "ec2:DescribeTags",
        "ec2:DescribeVpcs",
        "ec2:DescribeVpcPeeringConnections",
        "ec2:DescribeSecurityGroups",
        "ec2:DescribeSubnets",
        "ec2:DescribeAvailabilityZones",
        "ec2:DescribeRouteTables",
        "ec2:CreateTags",
        "ec2:DeleteTags",
        "ec2:CreateSecurityGroup",
        "ec2:AuthorizeSecurityGroupIngress",
        "ec2:RevokeSecurityGroupIngress",
        "ec2:DeleteSecurityGroup",
        "ec2:ModifySecurityGroupRules",
        "ec2:CreateSecurityGroupRule",
        "ec2:DeleteSecurityGroupRule",
        "ec2:CreateNetworkInterface",
        "ec2:DeleteNetworkInterface",
        "ec2:DescribeNetworkInterfaces",
        "ec2:CreateSecurityGroupEgress",
        "ec2:AuthorizeSecurityGroupEgress",
        "ec2:RevokeSecurityGroupEgress",
        "ec2:DeleteSecurityGroupEgress",
        "elasticloadbalancing:DescribeLoadBalancers",
        "elasticloadbalancing:DescribeLoadBalancerAttributes",
        "elasticloadbalancing:DescribeListeners",
        "elasticloadbalancing:DescribeRules",
        "elasticloadbalancing:DescribeTargetGroups",
        "elasticloadbalancing:DescribeTargetGroupAttributes",
        "elasticloadbalancing:DescribeTargetHealth",
        "elasticloadbalancing:CreateLoadBalancer",
        "elasticloadbalancing:DeleteLoadBalancer",
        "elasticloadbalancing:ModifyLoadBalancerAttributes",
        "elasticloadbalancing:AddTags",
        "elasticloadbalancing:RemoveTags",
        "elasticloadbalancing:CreateListener",
        "elasticloadbalancing:DeleteListener",
        "elasticloadbalancing:CreateRule",
        "elasticloadbalancing:DeleteRule",
        "elasticloadbalancing:ModifyListener",
        "elasticloadbalancing:ModifyRule",
        "elasticloadbalancing:SetSecurityGroups",
        "elasticloadbalancing:SetSubnets",
        "elasticloadbalancing:SetIpAddressType",
        "elasticloadbalancing:CreateTargetGroup",
        "elasticloadbalancing:DeleteTargetGroup",
        "elasticloadbalancing:ModifyTargetGroup",
        "elasticloadbalancing:ModifyTargetGroupAttributes",
        "elasticloadbalancing:RegisterTargets",
        "elasticloadbalancing:DeregisterTargets",
        "elasticloadbalancing:SetWebACL",
        "elasticloadbalancing:ModifyLoadBalancer",
        "elasticloadbalancing:DescribeSSLPolicies",
        "acm:DescribeCertificate",
        "acm:ListCertificates",
        "acm:GetCertificate",
        "wafv2:GetWebACL",
        "wafv2:GetWebACLForResource",
        "wafv2:AssociateWebACL",
        "wafv2:DisassociateWebACL",
        "tag:GetResources",
        "tag:TagResources",
        "tag:UntagResources"
      ],
      "Resource": "*"
    }
  ]
}